COPYING.md
MANIFEST.in
README.md
setup.py
djungle/__init__.py
djungle/sizzle/__init__.py
djungle/sizzle/static/.DS_Store
djungle/sizzle/static/djungle/sizzle.full.js
djungle/sizzle/static/djungle/sizzle.js
djungle_sizzle.egg-info/PKG-INFO
djungle_sizzle.egg-info/SOURCES.txt
djungle_sizzle.egg-info/dependency_links.txt
djungle_sizzle.egg-info/namespace_packages.txt
djungle_sizzle.egg-info/not-zip-safe
djungle_sizzle.egg-info/requires.txt
djungle_sizzle.egg-info/top_level.txt